{
  "/_not-found/page": "app/_not-found/page.js",
  "/(services)/auth/page": "app/(services)/auth/page.js",
  "/(services)/feed/page": "app/(services)/feed/page.js",
  "/(services)/payment/success/page": "app/(services)/payment/success/page.js",
  "/(services)/offers/page": "app/(services)/offers/page.js",
  "/(services)/post/success/page": "app/(services)/post/success/page.js",
  "/(services)/post/page": "app/(services)/post/page.js",
  "/home/page": "app/home/page.js",
  "/(services)/reserved/page": "app/(services)/reserved/page.js",
  "/chat/[googleId]/page": "app/chat/[googleId]/page.js",
  "/page": "app/page.js",
  "/items/[id]/page": "app/items/[id]/page.js",
  "/settings/page": "app/settings/page.js",
  "/settings/dashboard/page": "app/settings/dashboard/page.js",
  "/shop/page": "app/shop/page.js",
  "/social-profile/[googleId]/page": "app/social-profile/[googleId]/page.js",
  "/social-profile/page": "app/social-profile/page.js"
}